gressify/__init__.py
gressify/__main__.py
gressify-0.0.1.dist-info/METADATA
gressify-0.0.1.dist-info/WHEEL
gressify-0.0.1.dist-info/entry_points.txt
gressify-0.0.1.dist-info/top_level.txt
gressify-0.0.1.dist-info/RECORD
